rpi_lcd_i2c/__init__.py
rpi_lcd_i2c/i2c_lcd.py
rpi_lcd_i2c/lcd_api.py
rpi_lcd_i2c-2.0.0.dist-info/licenses/LICENSE
rpi_lcd_i2c-2.0.0.dist-info/METADATA
rpi_lcd_i2c-2.0.0.dist-info/WHEEL
rpi_lcd_i2c-2.0.0.dist-info/top_level.txt
rpi_lcd_i2c-2.0.0.dist-info/RECORD
