Metadata-Version: 2.4
Name: rpi_lcd_i2c
Version: 2.0.0
Summary: HD44780 I2C LCD driver for Raspberry Pi (Bookworm)
Home-page: https://github.com/Sam67-coder/rpi-lcd-i2c
Author: Samarth Joneja
Author-email: Samarth.Joneja@gmail.com
License: MIT
Classifier: Programming Language :: Python :: 3
Classifier: Operating System :: POSIX :: Linux
Classifier: Topic :: System :: Hardware
Requires-Python: >=3.9
License-File: LICENSE
Requires-Dist: smbus2
Dynamic: author
Dynamic: author-email
Dynamic: classifier
Dynamic: description
Dynamic: description-content-type
Dynamic: home-page
Dynamic: license
Dynamic: license-file
Dynamic: requires-dist
Dynamic: requires-python
Dynamic: summary
